joelclui/__init__.py
joelclui/joelclui.py
joelclui/format/CONSTANTS.py
joelclui/format/__init__.py
joelclui/format/format.py
joelclui/navigation/__init__.py
joelclui/navigation/move.py
JoelCLUI-1.1.18.dist-info/LICENSE
JoelCLUI-1.1.18.dist-info/METADATA
JoelCLUI-1.1.18.dist-info/WHEEL
JoelCLUI-1.1.18.dist-info/top_level.txt
JoelCLUI-1.1.18.dist-info/RECORD
