Metadata-Version: 2.1
Name: JoelCLUI
Version: 1.1.18
Summary: A command line user interface tool
Author-email: Joel Grayson <joel@joelgrayson.com>
License: MIT License
Project-URL: Homepage, https://github.com/JoelGrayson/JoelCLUI
Project-URL: Bug Tracker, https://github.com/JoelGrayson/JoelCLUI/issues
Classifier: Programming Language :: Python :: 3
Classifier: License :: OSI Approved :: MIT License
Classifier: Operating System :: OS Independent
Requires-Python: >=3.7
License-File: LICENSE
